freebsd_sysctl/__init__.py
freebsd_sysctl/__version__.py
freebsd_sysctl/libc.py
freebsd_sysctl-0.0.1.dist-info/LICENSE.txt
freebsd_sysctl-0.0.1.dist-info/METADATA
freebsd_sysctl-0.0.1.dist-info/WHEEL
freebsd_sysctl-0.0.1.dist-info/top_level.txt
freebsd_sysctl-0.0.1.dist-info/RECORD
